setup.py
package_gua/Binomialdistribution.py
package_gua/Gaussiandistribution.py
package_gua/Generaldistribution.py
package_gua/__init__.py
package_gua.egg-info/PKG-INFO
package_gua.egg-info/SOURCES.txt
package_gua.egg-info/dependency_links.txt
package_gua.egg-info/not-zip-safe
package_gua.egg-info/top_level.txt