Metadata-Version: 1.0
Name: package-gua
Version: 0.1
Summary: package_gua
Home-page: UNKNOWN
Author: Andrew
Author-email: UNKNOWN
License: UNKNOWN
Platform: UNKNOWN
